dariusVision/__init__.py
dariusVision/cam.py
dariusVision/realsense2.py
dariusVision/utils.py
dariusVision-0.0.7.dist-info/LICENSE
dariusVision-0.0.7.dist-info/METADATA
dariusVision-0.0.7.dist-info/WHEEL
dariusVision-0.0.7.dist-info/top_level.txt
dariusVision-0.0.7.dist-info/RECORD
