Metadata-Version: 2.1
Name: dariusVision
Version: 0.0.7
Summary: Real-time video streaming utility for capturing the latest frame
Home-page: https://github.com/gbox3d/dariusVision.git
Author: gbox3d
Author-email: gbox3d@gmail.com
Classifier: Development Status :: 3 - Alpha
Classifier: Intended Audience :: Developers
Classifier: License :: OSI Approved :: MIT License
Classifier: Programming Language :: Python :: 3
License-File: LICENSE
Requires-Dist: numpy
